{
  "soal": [
    {
      "nomor": 1,
      "soalCerita": {
        "text": "",
        "imageUrls": []
      },
      "soal": {
        "text": "Nilai maksimum fungsi kuadrat f adalah 80 dan grafik fungsi tersebut melalui titik (–2, 0) dan (6, 0). Grafik fungsi tersebut juga melalui titik (3, c) dengan c =",
        "imageUrls": []
      },
      "opsiSoal": [
        {
          "text": "55",
          "imageUrls": []
        },
        {
          "text": "60",
          "imageUrls": []
        },
        {
          "text": "65",
          "imageUrls": []
        },
        {
          "text": "70",
          "imageUrls": []
        },
        {
          "text": "75",
          "imageUrls": []
        }
      ],
      "jawaban": {
        "text": "75",
        "imageUrls": []
      }
    },
    {
      "nomor": 2,
      "soalCerita": {
        "text": "",
        "imageUrls": []
      },
      "soal": {
        "text": "Paragraf untuk soal nomor 2, 3, dan 4.Bilangan empat angka a182 kurang dari 6000.Jika bilangan tersebut dibagi 3 bersisa 2, maka a =",
        "imageUrls": []
      },
      "opsiSoal": [
        {
          "text": "1",
          "imageUrls": []
        },
        {
          "text": "2",
          "imageUrls": []
        },
        {
          "text": "3",
          "imageUrls": []
        },
        {
          "text": "4",
          "imageUrls": []
        },
        {
          "text": "5",
          "imageUrls": []
        }
      ],
      "jawaban": {
        "text": "3",
        "imageUrls": []
      }
    },
    {
      "nomor": 3,
      "soalCerita": {
        "text": "",
        "imageUrls": []
      },
      "soal": {
        "text": "Paragraf untuk soal nomor 2, 3, dan 4.Bilangan empat angka a182 kurang dari 6000.Banyak faktor prima dari bilangan empat angka tersebut adalah ...",
        "imageUrls": []
      },
      "opsiSoal": [
        {
          "text": "2",
          "imageUrls": []
        },
        {
          "text": "3",
          "imageUrls": []
        },
        {
          "text": "4",
          "imageUrls": []
        },
        {
          "text": "5",
          "imageUrls": []
        },
        {
          "text": "6",
          "imageUrls": []
        }
      ],
      "jawaban": {
        "text": "3",
        "imageUrls": []
      }
    },
    {
      "nomor": 4,
      "soalCerita": {
        "text": "",
        "imageUrls": []
      },
      "soal": {
        "text": "Paragraf untuk soal nomor 2, 3, dan 4.Bilangan empat angka a182 kurang dari 6000.Banyak faktor positif dari bilangan empat angka tersebut adalah ...",
        "imageUrls": []
      },
      "opsiSoal": [
        {
          "text": "16",
          "imageUrls": []
        },
        {
          "text": "15",
          "imageUrls": []
        },
        {
          "text": "12",
          "imageUrls": []
        },
        {
          "text": "10",
          "imageUrls": []
        },
        {
          "text": "8",
          "imageUrls": []
        }
      ],
      "jawaban": {
        "text": "8",
        "imageUrls": []
      }
    },
    {
      "nomor": 5,
      "soalCerita": {
        "text": "",
        "imageUrls": []
      },
      "soal": {
        "text": "Perhatikan data p, 2, - 5, 7!Pernyataan mana saja yang bernilai benar berdasarkan data di atas?(1)   Jangkauan data tersebut 15 jika p = -8.(2)   Rata-rata data tersebut 2 jika p = 4.(3)   Modus data tersebut 2 jika p = 2.(4)   Median data tersebut 3 jika p = 6.",
        "imageUrls": []
      },
      "opsiSoal": [
        {
          "text": "(1), (2), dan (3) SAJA yang benar.",
          "imageUrls": []
        },
        {
          "text": "(1) dan (3) SAJA yang benar.",
          "imageUrls": []
        },
        {
          "text": "(2) dan (4) SAJA yang benar.",
          "imageUrls": []
        },
        {
          "text": "HANYA (4) yang benar.",
          "imageUrls": []
        },
        {
          "text": "SEMUA pilihan benar.",
          "imageUrls": []
        }
      ],
      "jawaban": {
        "text": "(1), (2), dan (3) SAJA yang benar.",
        "imageUrls": []
      }
    },
    {
      "nomor": 7,
      "soalCerita": {
        "text": "",
        "imageUrls": []
      },
      "soal": {
        "text": "",
        "imageUrls": [
          "{{root_media}}/1714124132929_0rkrgq.png"
        ]
      },
      "opsiSoal": [
        {
          "text": "0",
          "imageUrls": []
        },
        {
          "text": "1",
          "imageUrls": []
        },
        {
          "text": "2",
          "imageUrls": []
        },
        {
          "text": "3",
          "imageUrls": []
        },
        {
          "text": "4",
          "imageUrls": []
        }
      ],
      "jawaban": {
        "text": "2",
        "imageUrls": []
      }
    },
    {
      "nomor": 8,
      "soalCerita": {
        "text": "",
        "imageUrls": []
      },
      "soal": {
        "text": "",
        "imageUrls": [
          "{{root_media}}/1714124306719_qm1qev.png"
        ]
      },
      "opsiSoal": [
        {
          "text": "P > Q.",
          "imageUrls": []
        },
        {
          "text": "Q > P.",
          "imageUrls": []
        },
        {
          "text": "P = Q.",
          "imageUrls": []
        },
        {
          "text": "Tidak dapat ditentukan hubungan P dan Q.",
          "imageUrls": []
        }
      ],
      "jawaban": {
        "text": "P = Q.",
        "imageUrls": []
      }
    },
    {
      "nomor": 9,
      "soalCerita": {
        "text": "",
        "imageUrls": []
      },
      "soal": {
        "text": "Perhatikan barisan bilangan real 4, a, 12, ...!Apakah 32 merupakan salah satu suku barisan tersebut?Putuskan apakah pernyataan (1) dan (2) berikut cukup untuk menjawab pertanyaan tersebut.(1)   Barisan tersebut adalah barisan aritmetika.(2)   Barisan tersebut adalah barisan geometri.",
        "imageUrls": []
      },
      "opsiSoal": [
        {
          "text": "Pernyataan (1) SAJA cukup untuk menjawab pertanyaan tetapi pernyataan (2) SAJA tidak cukup.",
          "imageUrls": []
        },
        {
          "text": "Pernyataan (2) SAJA cukup untuk menjawab pertanyaan tetapi pernyataan (1) SAJA tidak cukup.",
          "imageUrls": []
        },
        {
          "text": "Pernyataan (1) dan (2) cukup untuk menjawab pertanyaan, tetapi salah satu dari keduanya tidak cukup.",
          "imageUrls": []
        },
        {
          "text": "Pernyataan (1) ataupun pernyataan (2) SAJA sudah cukup untuk menjawab pertanyaan.",
          "imageUrls": []
        },
        {
          "text": "Pernyataan (1) dan pernyataan (2) tidak cukup untuk menjawab pertanyaan.",
          "imageUrls": []
        }
      ],
      "jawaban": {
        "text": "Pernyataan (1) ataupun pernyataan (2) SAJA sudah cukup untuk menjawab pertanyaan.",
        "imageUrls": []
      }
    },
    {
      "nomor": 10,
      "soalCerita": {
        "text": "",
        "imageUrls": []
      },
      "soal": {
        "text": "Jawablah soal berikut dengan mengetikkan jawaban berupa angka (bilangan bulat tanpa koma atau titik)!",
        "imageUrls": [
          "{{root_media}}/1714124551322_e4jrjj.png"
        ]
      },
      "jawaban": {
        "text": "24",
        "imageUrls": []
      }
    },
    {
      "nomor": 11,
      "soalCerita": {
        "text": "",
        "imageUrls": []
      },
      "soal": {
        "text": "Bilangan berikut yang habis dibagi 3, tetapi tidak habis dibagi 4 adalah",
        "imageUrls": []
      },
      "opsiSoal": [
        {
          "text": "34524",
          "imageUrls": []
        },
        {
          "text": "12342",
          "imageUrls": []
        },
        {
          "text": "23136",
          "imageUrls": []
        },
        {
          "text": "12348",
          "imageUrls": []
        },
        {
          "text": "52213",
          "imageUrls": []
        }
      ],
      "jawaban": {
        "text": "12342",
        "imageUrls": []
      }
    },
    {
      "nomor": 12,
      "soalCerita": {
        "text": "",
        "imageUrls": []
      },
      "soal": {
        "text": "",
        "imageUrls": [
          "{{root_media}}/1714124803859_eerddd.png"
        ]
      },
      "opsiSoal": [
        {
          "text": "",
          "imageUrls": [
            "{{root_media}}/1714124803859_tf5fpl.png"
          ]
        },
        {
          "text": "",
          "imageUrls": [
            "{{root_media}}/1714124803860_salrkd.png"
          ]
        },
        {
          "text": "",
          "imageUrls": [
            "{{root_media}}/1714124803860_ziyj9x.png"
          ]
        },
        {
          "text": "",
          "imageUrls": [
            "{{root_media}}/1714124803860_h91krr.png"
          ]
        },
        {
          "text": "",
          "imageUrls": [
            "{{root_media}}/1714124803860_th5dkw.png"
          ]
        }
      ],
      "jawaban": {
        "text": "",
        "imageUrls": [
          "{{root_media}}/1714124803860_ziyj9x.png"
        ]
      }
    },
    {
      "nomor": 13,
      "soalCerita": {
        "text": "",
        "imageUrls": []
      },
      "soal": {
        "text": "",
        "imageUrls": [
          "{{root_media}}/1714124898003_nfml4o.png"
        ]
      },
      "opsiSoal": [
        {
          "text": "kurva terbuka ke atas.",
          "imageUrls": []
        },
        {
          "text": "kurva terbuka ke bawah.",
          "imageUrls": []
        },
        {
          "text": "kurva memotong sumbu y positif.",
          "imageUrls": []
        },
        {
          "text": "kurva memotong sumbu y negatif.",
          "imageUrls": []
        },
        {
          "text": "titik puncak berada di kuadran II.",
          "imageUrls": []
        }
      ],
      "jawaban": {
        "text": "kurva memotong sumbu y positif.",
        "imageUrls": []
      }
    },
    {
      "nomor": 14,
      "soalCerita": {
        "text": "",
        "imageUrls": []
      },
      "soal": {
        "text": "Garis dengan persamaan mana saja yang memotong garis x + 2y = 10 dan x + y = 6 di dua  titik berbeda?(1)   3x + y = 10(2)   3x + 6y = 7(3)   3x + 3y = 1 (4)   3x + 2y = 5",
        "imageUrls": []
      },
      "opsiSoal": [
        {
          "text": "1, 2, dan 3 saja yang benar.",
          "imageUrls": []
        },
        {
          "text": "1 dan 3 saja yang benar.",
          "imageUrls": []
        },
        {
          "text": "2 dan 4 saja yang benar.",
          "imageUrls": []
        },
        {
          "text": "Hanya 4 yang benar.",
          "imageUrls": []
        },
        {
          "text": "Semua pilihan benar.",
          "imageUrls": []
        }
      ],
      "jawaban": {
        "text": "Hanya 4 yang benar.",
        "imageUrls": []
      }
    },
    {
      "nomor": 15,
      "soalCerita": {
        "text": "",
        "imageUrls": []
      },
      "soal": {
        "text": "Diberikan kumpulan data 2, 4, 5, bBerapakah banyaknya dari empat pernyataan berikut yang bernilai benar berdasarkan informasi di atas?(1)   Rata-rata kumpulan data tersebut 5 bila b = 9(2)   Median kumpulan data tersebut 4 bila b = 2(3)   Jangkauan kumpulan data tersebut 8 bila b = 10(4)   Modus kumpulan data tersebut 4 bila b = 4",
        "imageUrls": []
      },
      "opsiSoal": [
        {
          "text": "0",
          "imageUrls": []
        },
        {
          "text": "1",
          "imageUrls": []
        },
        {
          "text": "2",
          "imageUrls": []
        },
        {
          "text": "3",
          "imageUrls": []
        },
        {
          "text": "4",
          "imageUrls": []
        }
      ],
      "jawaban": {
        "text": "3",
        "imageUrls": []
      }
    },
    {
      "nomor": 16,
      "soalCerita": {
        "text": "",
        "imageUrls": []
      },
      "soal": {
        "text": "Tiga bola diambil dari sebuah kotak yang berisi 2 bola merah dan 4 bola kuning. Pada percobaan mengambil tiga bola sekaligus, misalkan A menyatakan kejadian terambilnya 1 bola merah dan 2 bola kuning dan P(A) menyatakan peluang kejadian A.Berdasarkan informasi yang diberikan manakah hubungan antara kuantitas P dan Q berikut yang benar?",
        "imageUrls": [
          "{{root_media}}/1714125268115_6j7atg.png"
        ]
      },
      "opsiSoal": [
        {
          "text": "P > Q.",
          "imageUrls": []
        },
        {
          "text": "Q > P.",
          "imageUrls": []
        },
        {
          "text": "P = Q.",
          "imageUrls": []
        },
        {
          "text": "Tidak dapat ditentukan hubungan P dan Q.",
          "imageUrls": []
        }
      ],
      "jawaban": {
        "text": "P = Q.",
        "imageUrls": []
      }
    },
    {
      "nomor": 17,
      "soalCerita": {
        "text": "",
        "imageUrls": []
      },
      "soal": {
        "text": "",
        "imageUrls": [
          "{{root_media}}/1714125361179_b8ykbc.png"
        ]
      },
      "opsiSoal": [
        {
          "text": "P > Q.",
          "imageUrls": []
        },
        {
          "text": "Q > P.",
          "imageUrls": []
        },
        {
          "text": "P = Q.",
          "imageUrls": []
        },
        {
          "text": "Tidak dapat ditentukan hubungan P dan Q.",
          "imageUrls": []
        }
      ],
      "jawaban": {
        "text": "Tidak dapat ditentukan hubungan P dan Q.",
        "imageUrls": []
      }
    },
    {
      "nomor": 18,
      "soalCerita": {
        "text": "",
        "imageUrls": []
      },
      "soal": {
        "text": "",
        "imageUrls": [
          "{{root_media}}/1714125844458_qtn7lr.png"
        ]
      },
      "opsiSoal": [
        {
          "text": "Semua pernyataan benar.",
          "imageUrls": []
        },
        {
          "text": "Pernyataan 1 dan 2 saja yang benar.",
          "imageUrls": []
        },
        {
          "text": "Pernyataan 2 dan 3 saja yang benar.",
          "imageUrls": []
        },
        {
          "text": "Pernyataan 3 saja yang benar.",
          "imageUrls": []
        },
        {
          "text": "Tidak ada pernyataan yang benar.",
          "imageUrls": []
        }
      ],
      "jawaban": {
        "text": "Pernyataan 1 dan 2 saja yang benar.",
        "imageUrls": []
      }
    },
    {
      "nomor": 19,
      "soalCerita": {
        "text": "",
        "imageUrls": []
      },
      "soal": {
        "text": "",
        "imageUrls": [
          "{{root_media}}/1714126031769_rkepjw.png"
        ]
      },
      "opsiSoal": [
        {
          "text": "Pernyataan 1 saja cukup untuk menjawab pertanyaan, tetapi 2 saja tidak cukup.",
          "imageUrls": []
        },
        {
          "text": "Pernyataan 2 saja cukup untuk menjawab pertanyaan, tetapi 1 saja tidak cukup.",
          "imageUrls": []
        },
        {
          "text": "Pernyataan 1 dan 2 cukup untuk menjawab pertanyaan, tetapi salah satu dari keduanya tidak cukup.",
          "imageUrls": []
        },
        {
          "text": "Pernyataan 1 atau pernyataan 2 saja sudah cukup untuk menjawab pertanyaan.",
          "imageUrls": []
        },
        {
          "text": "Pernyataan 1 dan pernyataan 2 tidak cukup untuk menjawab pertanyaan.",
          "imageUrls": []
        }
      ],
      "jawaban": {
        "text": "Pernyataan 1 saja cukup untuk menjawab pertanyaan, tetapi 2 saja tidak cukup.",
        "imageUrls": []
      }
    },
    {
      "nomor": 20,
      "soalCerita": {
        "text": "",
        "imageUrls": []
      },
      "soal": {
        "text": "Diketahui b = 3c dan b - d = 6Apakah d bilangan positif?Putuskan apakah pernyataan 1 dan 2 berikut cukup untuk menjawab pertanyaan tersebut?(1)   d = c - 4(2)   b - 4c = 0",
        "imageUrls": []
      },
      "opsiSoal": [
        {
          "text": "Pernyataan 1 saja cukup untuk menjawab pertanyaan, tetapi 2 saja tidak cukup.",
          "imageUrls": []
        },
        {
          "text": "Pernyataan 2 saja cukup untuk menjawab pertanyaan, tetapi 1 saja tidak cukup.",
          "imageUrls": []
        },
        {
          "text": "Pernyataan 1 dan 2 cukup untuk menjawab pertanyaan, tetapi salah satu dari keduanya tidak cukup.",
          "imageUrls": []
        },
        {
          "text": "Pernyataan 1 atau pernyataan 2 saja sudah cukup untuk menjawab pertanyaan.",
          "imageUrls": []
        },
        {
          "text": "Pernyataan 1 dan pernyataan 2 tidak cukup untuk menjawab pertanyaan.",
          "imageUrls": []
        }
      ],
      "jawaban": {
        "text": "Pernyataan 1 atau pernyataan 2 saja sudah cukup untuk menjawab pertanyaan.",
        "imageUrls": []
      }
    }
  ],
  "solusi": [
    {
      "nomor": 1,
      "solusi": "https://assets.ganeshaoperationexpert.com/banksoal/media/1714121704340_xvz3pn.png"
    },
    {
      "nomor": 2,
      "solusi": "Bilangan habis dibagi 3, maka jumlah digit bilangan tersebut kelipatan 3.a + 1 + 8 + 2 = (a + 9) + 2agar a182 kurang dari 6000 dan dibagi 3 sisa 2, maka nilai a = 3."
    },
    {
      "nomor": 3,
      "solusi": "3182 = 2 × 37 × 43Banyak faktor prima ada 3."
    },
    {
      "nomor": 4,
      "solusi": "3182 = 1 × 31823182 = 2 × 15913182 = 37 × 863182 = 43 × 74Banyak faktor positif dari angka 3182 ada 8."
    },
    {
      "nomor": 5,
      "solusi": "https://assets.ganeshaoperationexpert.com/banksoal/media/1714123826201_ucbmz5.png"
    },
    {
      "nomor": 6,
      "solusi": "https://assets.ganeshaoperationexpert.com/banksoal/media/1714123942122_9fcrbg.png"
    },
    {
      "nomor": 7,
      "solusi": "https://assets.ganeshaoperationexpert.com/banksoal/media/1714124132930_rx7nns.png"
    },
    {
      "nomor": 7,
      "solusi": "https://assets.ganeshaoperationexpert.com/banksoal/media/1714124132930_x3pgzf.png"
    },
    {
      "nomor": 8,
      "solusi": "https://assets.ganeshaoperationexpert.com/banksoal/media/1714124306719_ieo9d0.png"
    },
    {
      "nomor": 9,
      "solusi": "https://assets.ganeshaoperationexpert.com/banksoal/media/1714124456458_67ucl1.png"
    },
    {
      "nomor": 10,
      "solusi": "https://assets.ganeshaoperationexpert.com/banksoal/media/1714124551322_tc3cim.png"
    },
    {
      "nomor": 11,
      "solusi": "https://assets.ganeshaoperationexpert.com/banksoal/media/1714124657793_q0wrfs.png"
    },
    {
      "nomor": 12,
      "solusi": "https://assets.ganeshaoperationexpert.com/banksoal/media/1714124803859_6jubq7.png"
    },
    {
      "nomor": 13,
      "solusi": "https://assets.ganeshaoperationexpert.com/banksoal/media/1714124898004_03rn6x.png"
    },
    {
      "nomor": 14,
      "solusi": "https://assets.ganeshaoperationexpert.com/banksoal/media/1714124994953_de9apr.png"
    },
    {
      "nomor": 14,
      "solusi": "https://assets.ganeshaoperationexpert.com/banksoal/media/1714125158107_z4gyug.png"
    },
    {
      "nomor": 15,
      "solusi": "https://assets.ganeshaoperationexpert.com/banksoal/media/1714125084995_60ldef.png"
    },
    {
      "nomor": 16,
      "solusi": "https://assets.ganeshaoperationexpert.com/banksoal/media/1714125268115_kb4pa4.png"
    },
    {
      "nomor": 17,
      "solusi": "https://assets.ganeshaoperationexpert.com/banksoal/media/1714125361179_zporfc.png"
    },
    {
      "nomor": 18,
      "solusi": "https://assets.ganeshaoperationexpert.com/banksoal/media/1714125844458_cev2e4.png"
    },
    {
      "nomor": 19,
      "solusi": "https://assets.ganeshaoperationexpert.com/banksoal/media/1714126031769_24huw2.png"
    },
    {
      "nomor": 19,
      "solusi": "https://assets.ganeshaoperationexpert.com/banksoal/media/1714126031769_n4ogmz.png"
    },
    {
      "nomor": 20,
      "solusi": "https://assets.ganeshaoperationexpert.com/banksoal/media/1714126170592_2gzib6.png"
    },
    {
      "nomor": 20,
      "solusi": "https://assets.ganeshaoperationexpert.com/banksoal/media/1714126170592_vuzs9x.png"
    }
  ]
}